service_days/__init__.py
service_days/servicedays.py
service_days-0.0.7.dist-info/METADATA
service_days-0.0.7.dist-info/WHEEL
service_days-0.0.7.dist-info/licenses/LICENSE
service_days-0.0.7.dist-info/RECORD
