Metadata-Version: 2.1
Name: service-days
Version: 0.0.7
Summary: A tool to help calculate the number of 'work days' between two dates given a particular schedule.
Project-URL: Documentation, https://github.com/mcmasty/service-days#readme
Project-URL: Issues, https://github.com/mcmasty/service-days/issues
Project-URL: Source, https://github.com/mcmasty/service-days/
Author-email: Tyler McMaster <tyler@tlm13.com>
License-Expression: MIT
License-File: LICENSE
Classifier: Development Status :: 4 - Beta
Classifier: Programming Language :: Python
Classifier: Programming Language :: Python :: 3.10
Classifier: Programming Language :: Python :: 3.11
Classifier: Programming Language :: Python :: Implementation :: CPython
Classifier: Programming Language :: Python :: Implementation :: PyPy
Requires-Python: >=3.10
Requires-Dist: cowsay
Requires-Dist: mkdocs
Provides-Extra: dev
Requires-Dist: bump2version; extra == 'dev'
Requires-Dist: hatchling; extra == 'dev'
Requires-Dist: pyhamcrest; extra == 'dev'
Requires-Dist: pytest; extra == 'dev'
Requires-Dist: pytest-cov; extra == 'dev'
